aravind_package/__init__.py
aravind_package/package.py
aravind_package/tests/__init__.py
aravind_package/tests/test.py
aravind_package-0.1.0.dist-info/LICENSE
aravind_package-0.1.0.dist-info/METADATA
aravind_package-0.1.0.dist-info/WHEEL
aravind_package-0.1.0.dist-info/top_level.txt
aravind_package-0.1.0.dist-info/RECORD
